{".class": "MypyFile", "_fullname": "dynamic-scheme", "is_partial_stub_package": false, "is_stub": false, "names": {".class": "SymbolTable", "Any": {".class": "SymbolTableNode", "cross_ref": "typing.Any", "kind": "Gdef"}, "Ast": {".class": "SymbolTableNode", "kind": "Gdef", "node": {".class": "TypeAlias", "alias_tvars": [], "column": 0, "fullname": "dynamic-scheme.Ast", "line": 180, "no_args": false, "normalized": false, "target": {".class": "UnionType", "items": ["builtins.int", "builtins.float", "builtins.str", {".class": "Instance", "args": [{".class": "AnyType", "missing_import_name": null, "source_any": null, "type_of_any": 6}], "type_ref": "builtins.list"}]}}}, "Callable": {".class": "SymbolTableNode", "cross_ref": "typing.Callable", "kind": "Gdef"}, "J": {".class": "SymbolTableNode", "kind": "Tvar", "node": {".class": "TypeVarExpr", "fullname": "dynamic-scheme.J", "name": "J", "upper_bound": "builtins.object", "values": [], "variance": 0}}, "List": {".class": "SymbolTableNode", "cross_ref": "typing.List", "kind": "Gdef"}, "Parser": {".class": "SymbolTableNode", "kind": "Gdef", "node": {".class": "TypeAlias", "alias_tvars": ["T"], "column": 0, "fullname": "dynamic-scheme.Parser", "line": 12, "no_args": false, "normalized": false, "target": {".class": "CallableType", "arg_kinds": [0, 0], "arg_names": [null, null], "arg_types": ["builtins.str", "builtins.int"], "bound_args": [], "def_extras": {}, "fallback": "builtins.function", "implicit": false, "is_ellipsis_args": false, "name": null, "ret_type": {".class": "Instance", "args": [{".class": "TupleType", "fallback": {".class": "Instance", "args": [{".class": "AnyType", "missing_import_name": null, "source_any": null, "type_of_any": 6}], "type_ref": "builtins.tuple"}, "implicit": false, "items": [{".class": "UnboundType", "args": [], "name": "T"}, "builtins.int"]}], "type_ref": "builtins.list"}, "variables": []}}}, "ParserResult": {".class": "SymbolTableNode", "kind": "Gdef", "node": {".class": "TypeAlias", "alias_tvars": ["T"], "column": 0, "fullname": "dynamic-scheme.ParserResult", "line": 11, "no_args": false, "normalized": false, "target": {".class": "Instance", "args": [{".class": "TupleType", "fallback": {".class": "Instance", "args": [{".class": "AnyType", "missing_import_name": null, "source_any": null, "type_of_any": 6}], "type_ref": "builtins.tuple"}, "implicit": false, "items": [{".class": "UnboundType", "args": [], "name": "T"}, "builtins.int"]}], "type_ref": "builtins.list"}}}, "T": {".class": "SymbolTableNode", "kind": "Tvar", "node": {".class": "TypeVarExpr", "fullname": "dynamic-scheme.T", "name": "T", "upper_bound": "builtins.object", "values": [], "variance": 0}}, "Tuple": {".class": "SymbolTableNode", "cross_ref": "typing.Tuple", "kind": "Gdef"}, "TypeVar": {".class": "SymbolTableNode", "cross_ref": "typing.TypeVar", "kind": "Gdef"}, "Union": {".class": "SymbolTableNode", "cross_ref": "typing.Union", "kind": "Gdef"}, "__doc__": {".class": "SymbolTableNode", "kind": "Gdef", "node": {".class": "Var", "flags": [], "fullname": "dynamic-scheme.__doc__", "name": "__doc__", "type": "builtins.str"}}, "__file__": {".class": "SymbolTableNode", "kind": "Gdef", "node": {".class": "Var", "flags": [], "fullname": "dynamic-scheme.__file__", "name": "__file__", "type": "builtins.str"}}, "__name__": {".class": "SymbolTableNode", "kind": "Gdef", "node": {".class": "Var", "flags": [], "fullname": "dynamic-scheme.__name__", "name": "__name__", "type": "builtins.str"}}, "__package__": {".class": "SymbolTableNode", "kind": "Gdef", "node": {".class": "Var", "flags": [], "fullname": "dynamic-scheme.__package__", "name": "__package__", "type": "builtins.str"}}, "any_parser": {".class": "SymbolTableNode", "kind": "Gdef", "node": {".class": "FuncDef", "arg_kinds": [2], "arg_names": ["parsers"], "flags": [], "fullname": "dynamic-scheme.any_parser", "name": "any_parser", "type": {".class": "CallableType", "arg_kinds": [2], "arg_names": ["parsers"], "arg_types": [{".class": "CallableType", "arg_kinds": [0, 0], "arg_names": [null, null], "arg_types": ["builtins.str", "builtins.int"], "bound_args": [], "def_extras": {}, "fallback": "builtins.function", "implicit": false, "is_ellipsis_args": false, "name": null, "ret_type": {".class": "Instance", "args": [{".class": "TupleType", "fallback": {".class": "Instance", "args": [{".class": "AnyType", "missing_import_name": null, "source_any": null, "type_of_any": 6}], "type_ref": "builtins.tuple"}, "implicit": false, "items": [{".class": "TypeVarType", "fullname": "dynamic-scheme.T", "id": -1, "name": "T", "upper_bound": "builtins.object", "values": [], "variance": 0}, "builtins.int"]}], "type_ref": "builtins.list"}, "variables": []}], "bound_args": [], "def_extras": {"first_arg": null}, "fallback": "builtins.function", "implicit": false, "is_ellipsis_args": false, "name": "any_parser", "ret_type": {".class": "CallableType", "arg_kinds": [0, 0], "arg_names": [null, null], "arg_types": ["builtins.str", "builtins.int"], "bound_args": [], "def_extras": {}, "fallback": "builtins.function", "implicit": false, "is_ellipsis_args": false, "name": null, "ret_type": {".class": "Instance", "args": [{".class": "TupleType", "fallback": {".class": "Instance", "args": [{".class": "AnyType", "missing_import_name": null, "source_any": null, "type_of_any": 6}], "type_ref": "builtins.tuple"}, "implicit": false, "items": [{".class": "TypeVarType", "fullname": "dynamic-scheme.T", "id": -1, "name": "T", "upper_bound": "builtins.object", "values": [], "variance": 0}, "builtins.int"]}], "type_ref": "builtins.list"}, "variables": []}, "variables": [{".class": "TypeVarDef", "fullname": "dynamic-scheme.T", "id": -1, "name": "T", "upper_bound": "builtins.object", "values": [], "variance": 0}]}}}, "cast": {".class": "SymbolTableNode", "cross_ref": "typing.cast", "kind": "Gdef"}, "chain_parsers": {".class": "SymbolTableNode", "kind": "Gdef", "node": {".class": "FuncDef", "arg_kinds": [2], "arg_names": ["parsers"], "flags": [], "fullname": "dynamic-scheme.chain_parsers", "name": "chain_parsers", "type": {".class": "CallableType", "arg_kinds": [2], "arg_names": ["parsers"], "arg_types": [{".class": "CallableType", "arg_kinds": [0, 0], "arg_names": [null, null], "arg_types": ["builtins.str", "builtins.int"], "bound_args": [], "def_extras": {}, "fallback": "builtins.function", "implicit": false, "is_ellipsis_args": false, "name": null, "ret_type": {".class": "Instance", "args": [{".class": "TupleType", "fallback": {".class": "Instance", "args": [{".class": "AnyType", "missing_import_name": null, "source_any": null, "type_of_any": 6}], "type_ref": "builtins.tuple"}, "implicit": false, "items": ["builtins.str", "builtins.int"]}], "type_ref": "builtins.list"}, "variables": []}], "bound_args": [], "def_extras": {"first_arg": null}, "fallback": "builtins.function", "implicit": false, "is_ellipsis_args": false, "name": "chain_parsers", "ret_type": {".class": "CallableType", "arg_kinds": [0, 0], "arg_names": [null, null], "arg_types": ["builtins.str", "builtins.int"], "bound_args": [], "def_extras": {}, "fallback": "builtins.function", "implicit": false, "is_ellipsis_args": false, "name": null, "ret_type": {".class": "Instance", "args": [{".class": "TupleType", "fallback": {".class": "Instance", "args": [{".class": "AnyType", "missing_import_name": null, "source_any": null, "type_of_any": 6}], "type_ref": "builtins.tuple"}, "implicit": false, "items": ["builtins.str", "builtins.int"]}], "type_ref": "builtins.list"}, "variables": []}, "variables": []}}}, "complete_parser": {".class": "SymbolTableNode", "kind": "Gdef", "node": {".class": "FuncDef", "arg_kinds": [0], "arg_names": ["p"], "flags": [], "fullname": "dynamic-scheme.complete_parser", "name": "complete_parser", "type": {".class": "CallableType", "arg_kinds": [0], "arg_names": ["p"], "arg_types": [{".class": "CallableType", "arg_kinds": [0, 0], "arg_names": [null, null], "arg_types": ["builtins.str", "builtins.int"], "bound_args": [], "def_extras": {}, "fallback": "builtins.function", "implicit": false, "is_ellipsis_args": false, "name": null, "ret_type": {".class": "Instance", "args": [{".class": "TupleType", "fallback": {".class": "Instance", "args": [{".class": "AnyType", "missing_import_name": null, "source_any": null, "type_of_any": 6}], "type_ref": "builtins.tuple"}, "implicit": false, "items": [{".class": "TypeVarType", "fullname": "dynamic-scheme.T", "id": -1, "name": "T", "upper_bound": "builtins.object", "values": [], "variance": 0}, "builtins.int"]}], "type_ref": "builtins.list"}, "variables": []}], "bound_args": [], "def_extras": {"first_arg": null}, "fallback": "builtins.function", "implicit": false, "is_ellipsis_args": false, "name": "complete_parser", "ret_type": {".class": "CallableType", "arg_kinds": [0, 0], "arg_names": [null, null], "arg_types": ["builtins.str", "builtins.int"], "bound_args": [], "def_extras": {}, "fallback": "builtins.function", "implicit": false, "is_ellipsis_args": false, "name": null, "ret_type": {".class": "Instance", "args": [{".class": "TupleType", "fallback": {".class": "Instance", "args": [{".class": "AnyType", "missing_import_name": null, "source_any": null, "type_of_any": 6}], "type_ref": "builtins.tuple"}, "implicit": false, "items": [{".class": "TypeVarType", "fullname": "dynamic-scheme.T", "id": -1, "name": "T", "upper_bound": "builtins.object", "values": [], "variance": 0}, "builtins.int"]}], "type_ref": "builtins.list"}, "variables": []}, "variables": [{".class": "TypeVarDef", "fullname": "dynamic-scheme.T", "id": -1, "name": "T", "upper_bound": "builtins.object", "values": [], "variance": 0}]}}}, "debug_parser": {".class": "SymbolTableNode", "kind": "Gdef", "node": {".class": "FuncDef", "arg_kinds": [0], "arg_names": ["p"], "flags": [], "fullname": "dynamic-scheme.debug_parser", "name": "debug_parser", "type": {".class": "CallableType", "arg_kinds": [0], "arg_names": ["p"], "arg_types": [{".class": "CallableType", "arg_kinds": [0, 0], "arg_names": [null, null], "arg_types": ["builtins.str", "builtins.int"], "bound_args": [], "def_extras": {}, "fallback": "builtins.function", "implicit": false, "is_ellipsis_args": false, "name": null, "ret_type": {".class": "Instance", "args": [{".class": "TupleType", "fallback": {".class": "Instance", "args": [{".class": "AnyType", "missing_import_name": null, "source_any": null, "type_of_any": 6}], "type_ref": "builtins.tuple"}, "implicit": false, "items": [{".class": "TypeVarType", "fullname": "dynamic-scheme.T", "id": -1, "name": "T", "upper_bound": "builtins.object", "values": [], "variance": 0}, "builtins.int"]}], "type_ref": "builtins.list"}, "variables": []}], "bound_args": [], "def_extras": {"first_arg": null}, "fallback": "builtins.function", "implicit": false, "is_ellipsis_args": false, "name": "debug_parser", "ret_type": {".class": "CallableType", "arg_kinds": [0, 0], "arg_names": [null, null], "arg_types": ["builtins.str", "builtins.int"], "bound_args": [], "def_extras": {}, "fallback": "builtins.function", "implicit": false, "is_ellipsis_args": false, "name": null, "ret_type": {".class": "Instance", "args": [{".class": "TupleType", "fallback": {".class": "Instance", "args": [{".class": "AnyType", "missing_import_name": null, "source_any": null, "type_of_any": 6}], "type_ref": "builtins.tuple"}, "implicit": false, "items": [{".class": "TypeVarType", "fullname": "dynamic-scheme.T", "id": -1, "name": "T", "upper_bound": "builtins.object", "values": [], "variance": 0}, "builtins.int"]}], "type_ref": "builtins.list"}, "variables": []}, "variables": [{".class": "TypeVarDef", "fullname": "dynamic-scheme.T", "id": -1, "name": "T", "upper_bound": "builtins.object", "values": [], "variance": 0}]}}}, "escape_control_parser": {".class": "SymbolTableNode", "kind": "Gdef", "node": {".class": "Var", "flags": [], "fullname": "dynamic-scheme.escape_control_parser", "name": "escape_control_parser", "type": {".class": "CallableType", "arg_kinds": [0, 0], "arg_names": [null, null], "arg_types": ["builtins.str", "builtins.int"], "bound_args": [], "def_extras": {}, "fallback": "builtins.function", "implicit": false, "is_ellipsis_args": false, "name": null, "ret_type": {".class": "Instance", "args": [{".class": "TupleType", "fallback": {".class": "Instance", "args": [{".class": "AnyType", "missing_import_name": null, "source_any": null, "type_of_any": 6}], "type_ref": "builtins.tuple"}, "implicit": false, "items": ["builtins.str", "builtins.int"]}], "type_ref": "builtins.list"}, "variables": []}}}, "eval": {".class": "SymbolTableNode", "kind": "Gdef", "node": {".class": "FuncDef", "arg_kinds": [0], "arg_names": ["e"], "flags": [], "fullname": "dynamic-scheme.eval", "name": "eval", "type": {".class": "CallableType", "arg_kinds": [0], "arg_names": ["e"], "arg_types": ["builtins.str"], "bound_args": [], "def_extras": {"first_arg": null}, "fallback": "builtins.function", "implicit": false, "is_ellipsis_args": false, "name": "eval", "ret_type": {".class": "Instance", "args": [{".class": "TupleType", "fallback": {".class": "Instance", "args": [{".class": "AnyType", "missing_import_name": null, "source_any": null, "type_of_any": 6}], "type_ref": "builtins.tuple"}, "implicit": false, "items": [{".class": "UnionType", "items": ["builtins.int", "builtins.float", "builtins.str", {".class": "Instance", "args": [{".class": "AnyType", "missing_import_name": null, "source_any": null, "type_of_any": 6}], "type_ref": "builtins.list"}]}, "builtins.int"]}], "type_ref": "builtins.list"}, "variables": []}}}, "except_parser": {".class": "SymbolTableNode", "kind": "Gdef", "node": {".class": "FuncDef", "arg_kinds": [0], "arg_names": ["char"], "flags": [], "fullname": "dynamic-scheme.except_parser", "name": "except_parser", "type": {".class": "CallableType", "arg_kinds": [0], "arg_names": ["char"], "arg_types": ["builtins.str"], "bound_args": [], "def_extras": {"first_arg": null}, "fallback": "builtins.function", "implicit": false, "is_ellipsis_args": false, "name": "except_parser", "ret_type": {".class": "CallableType", "arg_kinds": [0, 0], "arg_names": [null, null], "arg_types": ["builtins.str", "builtins.int"], "bound_args": [], "def_extras": {}, "fallback": "builtins.function", "implicit": false, "is_ellipsis_args": false, "name": null, "ret_type": {".class": "Instance", "args": [{".class": "TupleType", "fallback": {".class": "Instance", "args": [{".class": "AnyType", "missing_import_name": null, "source_any": null, "type_of_any": 6}], "type_ref": "builtins.tuple"}, "implicit": false, "items": ["builtins.str", "builtins.int"]}], "type_ref": "builtins.list"}, "variables": []}, "variables": []}}}, "filter_char_parser": {".class": "SymbolTableNode", "kind": "Gdef", "node": {".class": "FuncDef", "arg_kinds": [0], "arg_names": ["f"], "flags": [], "fullname": "dynamic-scheme.filter_char_parser", "name": "filter_char_parser", "type": {".class": "CallableType", "arg_kinds": [0], "arg_names": ["f"], "arg_types": [{".class": "CallableType", "arg_kinds": [0], "arg_names": [null], "arg_types": ["builtins.str"], "bound_args": [], "def_extras": {}, "fallback": "builtins.function", "implicit": false, "is_ellipsis_args": false, "name": null, "ret_type": "builtins.bool", "variables": []}], "bound_args": [], "def_extras": {"first_arg": null}, "fallback": "builtins.function", "implicit": false, "is_ellipsis_args": false, "name": "filter_char_parser", "ret_type": {".class": "CallableType", "arg_kinds": [0, 0], "arg_names": [null, null], "arg_types": ["builtins.str", "builtins.int"], "bound_args": [], "def_extras": {}, "fallback": "builtins.function", "implicit": false, "is_ellipsis_args": false, "name": null, "ret_type": {".class": "Instance", "args": [{".class": "TupleType", "fallback": {".class": "Instance", "args": [{".class": "AnyType", "missing_import_name": null, "source_any": null, "type_of_any": 6}], "type_ref": "builtins.tuple"}, "implicit": false, "items": ["builtins.str", "builtins.int"]}], "type_ref": "builtins.list"}, "variables": []}, "variables": []}}}, "float_parser": {".class": "SymbolTableNode", "kind": "Gdef", "node": {".class": "Var", "flags": [], "fullname": "dynamic-scheme.float_parser", "name": "float_parser", "type": {".class": "CallableType", "arg_kinds": [0, 0], "arg_names": [null, null], "arg_types": ["builtins.str", "builtins.int"], "bound_args": [], "def_extras": {}, "fallback": "builtins.function", "implicit": false, "is_ellipsis_args": false, "name": null, "ret_type": {".class": "Instance", "args": [{".class": "TupleType", "fallback": {".class": "Instance", "args": [{".class": "AnyType", "missing_import_name": null, "source_any": null, "type_of_any": 6}], "type_ref": "builtins.tuple"}, "implicit": false, "items": [{".class": "UnionType", "items": ["builtins.int", "builtins.float", "builtins.str", {".class": "Instance", "args": [{".class": "AnyType", "missing_import_name": null, "source_any": null, "type_of_any": 6}], "type_ref": "builtins.list"}]}, "builtins.int"]}], "type_ref": "builtins.list"}, "variables": []}}}, "if_else_parser": {".class": "SymbolTableNode", "kind": "Gdef", "node": {".class": "FuncDef", "arg_kinds": [0, 0], "arg_names": ["p1", "p2"], "flags": [], "fullname": "dynamic-scheme.if_else_parser", "name": "if_else_parser", "type": {".class": "CallableType", "arg_kinds": [0, 0], "arg_names": ["p1", "p2"], "arg_types": [{".class": "CallableType", "arg_kinds": [0, 0], "arg_names": [null, null], "arg_types": ["builtins.str", "builtins.int"], "bound_args": [], "def_extras": {}, "fallback": "builtins.function", "implicit": false, "is_ellipsis_args": false, "name": null, "ret_type": {".class": "Instance", "args": [{".class": "TupleType", "fallback": {".class": "Instance", "args": [{".class": "AnyType", "missing_import_name": null, "source_any": null, "type_of_any": 6}], "type_ref": "builtins.tuple"}, "implicit": false, "items": [{".class": "TypeVarType", "fullname": "dynamic-scheme.T", "id": -1, "name": "T", "upper_bound": "builtins.object", "values": [], "variance": 0}, "builtins.int"]}], "type_ref": "builtins.list"}, "variables": []}, {".class": "CallableType", "arg_kinds": [0, 0], "arg_names": [null, null], "arg_types": ["builtins.str", "builtins.int"], "bound_args": [], "def_extras": {}, "fallback": "builtins.function", "implicit": false, "is_ellipsis_args": false, "name": null, "ret_type": {".class": "Instance", "args": [{".class": "TupleType", "fallback": {".class": "Instance", "args": [{".class": "AnyType", "missing_import_name": null, "source_any": null, "type_of_any": 6}], "type_ref": "builtins.tuple"}, "implicit": false, "items": [{".class": "TypeVarType", "fullname": "dynamic-scheme.T", "id": -1, "name": "T", "upper_bound": "builtins.object", "values": [], "variance": 0}, "builtins.int"]}], "type_ref": "builtins.list"}, "variables": []}], "bound_args": [], "def_extras": {"first_arg": null}, "fallback": "builtins.function", "implicit": false, "is_ellipsis_args": false, "name": "if_else_parser", "ret_type": {".class": "CallableType", "arg_kinds": [0, 0], "arg_names": [null, null], "arg_types": ["builtins.str", "builtins.int"], "bound_args": [], "def_extras": {}, "fallback": "builtins.function", "implicit": false, "is_ellipsis_args": false, "name": null, "ret_type": {".class": "Instance", "args": [{".class": "TupleType", "fallback": {".class": "Instance", "args": [{".class": "AnyType", "missing_import_name": null, "source_any": null, "type_of_any": 6}], "type_ref": "builtins.tuple"}, "implicit": false, "items": [{".class": "TypeVarType", "fullname": "dynamic-scheme.T", "id": -1, "name": "T", "upper_bound": "builtins.object", "values": [], "variance": 0}, "builtins.int"]}], "type_ref": "builtins.list"}, "variables": []}, "variables": [{".class": "TypeVarDef", "fullname": "dynamic-scheme.T", "id": -1, "name": "T", "upper_bound": "builtins.object", "values": [], "variance": 0}]}}}, "int_parser": {".class": "SymbolTableNode", "kind": "Gdef", "node": {".class": "Var", "flags": [], "fullname": "dynamic-scheme.int_parser", "name": "int_parser", "type": {".class": "CallableType", "arg_kinds": [0, 0], "arg_names": [null, null], "arg_types": ["builtins.str", "builtins.int"], "bound_args": [], "def_extras": {}, "fallback": "builtins.function", "implicit": false, "is_ellipsis_args": false, "name": null, "ret_type": {".class": "Instance", "args": [{".class": "TupleType", "fallback": {".class": "Instance", "args": [{".class": "AnyType", "missing_import_name": null, "source_any": null, "type_of_any": 6}], "type_ref": "builtins.tuple"}, "implicit": false, "items": [{".class": "UnionType", "items": ["builtins.int", "builtins.float", "builtins.str", {".class": "Instance", "args": [{".class": "AnyType", "missing_import_name": null, "source_any": null, "type_of_any": 6}], "type_ref": "builtins.list"}]}, "builtins.int"]}], "type_ref": "builtins.list"}, "variables": []}}}, "map_parser": {".class": "SymbolTableNode", "kind": "Gdef", "node": {".class": "FuncDef", "arg_kinds": [0, 0], "arg_names": ["f", "p"], "flags": [], "fullname": "dynamic-scheme.map_parser", "name": "map_parser", "type": {".class": "CallableType", "arg_kinds": [0, 0], "arg_names": ["f", "p"], "arg_types": [{".class": "CallableType", "arg_kinds": [0], "arg_names": [null], "arg_types": [{".class": "TypeVarType", "fullname": "dynamic-scheme.T", "id": -1, "name": "T", "upper_bound": "builtins.object", "values": [], "variance": 0}], "bound_args": [], "def_extras": {}, "fallback": "builtins.function", "implicit": false, "is_ellipsis_args": false, "name": null, "ret_type": {".class": "TypeVarType", "fullname": "dynamic-scheme.J", "id": -2, "name": "J", "upper_bound": "builtins.object", "values": [], "variance": 0}, "variables": []}, {".class": "CallableType", "arg_kinds": [0, 0], "arg_names": [null, null], "arg_types": ["builtins.str", "builtins.int"], "bound_args": [], "def_extras": {}, "fallback": "builtins.function", "implicit": false, "is_ellipsis_args": false, "name": null, "ret_type": {".class": "Instance", "args": [{".class": "TupleType", "fallback": {".class": "Instance", "args": [{".class": "AnyType", "missing_import_name": null, "source_any": null, "type_of_any": 6}], "type_ref": "builtins.tuple"}, "implicit": false, "items": [{".class": "TypeVarType", "fullname": "dynamic-scheme.T", "id": -1, "name": "T", "upper_bound": "builtins.object", "values": [], "variance": 0}, "builtins.int"]}], "type_ref": "builtins.list"}, "variables": []}], "bound_args": [], "def_extras": {"first_arg": null}, "fallback": "builtins.function", "implicit": false, "is_ellipsis_args": false, "name": "map_parser", "ret_type": {".class": "CallableType", "arg_kinds": [0, 0], "arg_names": [null, null], "arg_types": ["builtins.str", "builtins.int"], "bound_args": [], "def_extras": {}, "fallback": "builtins.function", "implicit": false, "is_ellipsis_args": false, "name": null, "ret_type": {".class": "Instance", "args": [{".class": "TupleType", "fallback": {".class": "Instance", "args": [{".class": "AnyType", "missing_import_name": null, "source_any": null, "type_of_any": 6}], "type_ref": "builtins.tuple"}, "implicit": false, "items": [{".class": "TypeVarType", "fullname": "dynamic-scheme.J", "id": -2, "name": "J", "upper_bound": "builtins.object", "values": [], "variance": 0}, "builtins.int"]}], "type_ref": "builtins.list"}, "variables": []}, "variables": [{".class": "TypeVarDef", "fullname": "dynamic-scheme.T", "id": -1, "name": "T", "upper_bound": "builtins.object", "values": [], "variance": 0}, {".class": "TypeVarDef", "fullname": "dynamic-scheme.J", "id": -2, "name": "J", "upper_bound": "builtins.object", "values": [], "variance": 0}]}}}, "map_parser_exception": {".class": "SymbolTableNode", "kind": "Gdef", "node": {".class": "FuncDef", "arg_kinds": [0, 0], "arg_names": ["f", "p"], "flags": [], "fullname": "dynamic-scheme.map_parser_exception", "name": "map_parser_exception", "type": {".class": "CallableType", "arg_kinds": [0, 0], "arg_names": ["f", "p"], "arg_types": [{".class": "CallableType", "arg_kinds": [0], "arg_names": [null], "arg_types": [{".class": "TypeVarType", "fullname": "dynamic-scheme.T", "id": -1, "name": "T", "upper_bound": "builtins.object", "values": [], "variance": 0}], "bound_args": [], "def_extras": {}, "fallback": "builtins.function", "implicit": false, "is_ellipsis_args": false, "name": null, "ret_type": {".class": "TypeVarType", "fullname": "dynamic-scheme.J", "id": -2, "name": "J", "upper_bound": "builtins.object", "values": [], "variance": 0}, "variables": []}, {".class": "CallableType", "arg_kinds": [0, 0], "arg_names": [null, null], "arg_types": ["builtins.str", "builtins.int"], "bound_args": [], "def_extras": {}, "fallback": "builtins.function", "implicit": false, "is_ellipsis_args": false, "name": null, "ret_type": {".class": "Instance", "args": [{".class": "TupleType", "fallback": {".class": "Instance", "args": [{".class": "AnyType", "missing_import_name": null, "source_any": null, "type_of_any": 6}], "type_ref": "builtins.tuple"}, "implicit": false, "items": [{".class": "TypeVarType", "fullname": "dynamic-scheme.T", "id": -1, "name": "T", "upper_bound": "builtins.object", "values": [], "variance": 0}, "builtins.int"]}], "type_ref": "builtins.list"}, "variables": []}], "bound_args": [], "def_extras": {"first_arg": null}, "fallback": "builtins.function", "implicit": false, "is_ellipsis_args": false, "name": "map_parser_exception", "ret_type": {".class": "CallableType", "arg_kinds": [0, 0], "arg_names": [null, null], "arg_types": ["builtins.str", "builtins.int"], "bound_args": [], "def_extras": {}, "fallback": "builtins.function", "implicit": false, "is_ellipsis_args": false, "name": null, "ret_type": {".class": "Instance", "args": [{".class": "TupleType", "fallback": {".class": "Instance", "args": [{".class": "AnyType", "missing_import_name": null, "source_any": null, "type_of_any": 6}], "type_ref": "builtins.tuple"}, "implicit": false, "items": [{".class": "TypeVarType", "fullname": "dynamic-scheme.J", "id": -2, "name": "J", "upper_bound": "builtins.object", "values": [], "variance": 0}, "builtins.int"]}], "type_ref": "builtins.list"}, "variables": []}, "variables": [{".class": "TypeVarDef", "fullname": "dynamic-scheme.T", "id": -1, "name": "T", "upper_bound": "builtins.object", "values": [], "variance": 0}, {".class": "TypeVarDef", "fullname": "dynamic-scheme.J", "id": -2, "name": "J", "upper_bound": "builtins.object", "values": [], "variance": 0}]}}}, "parser_from_characters": {".class": "SymbolTableNode", "kind": "Gdef", "node": {".class": "FuncDef", "arg_kinds": [0, 0], "arg_names": ["f", "convert"], "flags": [], "fullname": "dynamic-scheme.parser_from_characters", "name": "parser_from_characters", "type": {".class": "CallableType", "arg_kinds": [0, 0], "arg_names": ["f", "convert"], "arg_types": [{".class": "CallableType", "arg_kinds": [0], "arg_names": [null], "arg_types": ["builtins.str"], "bound_args": [], "def_extras": {}, "fallback": "builtins.function", "implicit": false, "is_ellipsis_args": false, "name": null, "ret_type": "builtins.bool", "variables": []}, {".class": "CallableType", "arg_kinds": [0], "arg_names": [null], "arg_types": ["builtins.str"], "bound_args": [], "def_extras": {}, "fallback": "builtins.function", "implicit": false, "is_ellipsis_args": false, "name": null, "ret_type": {".class": "TypeVarType", "fullname": "dynamic-scheme.T", "id": -1, "name": "T", "upper_bound": "builtins.object", "values": [], "variance": 0}, "variables": []}], "bound_args": [], "def_extras": {"first_arg": null}, "fallback": "builtins.function", "implicit": false, "is_ellipsis_args": false, "name": "parser_from_characters", "ret_type": {".class": "CallableType", "arg_kinds": [0, 0], "arg_names": [null, null], "arg_types": ["builtins.str", "builtins.int"], "bound_args": [], "def_extras": {}, "fallback": "builtins.function", "implicit": false, "is_ellipsis_args": false, "name": null, "ret_type": {".class": "Instance", "args": [{".class": "TupleType", "fallback": {".class": "Instance", "args": [{".class": "AnyType", "missing_import_name": null, "source_any": null, "type_of_any": 6}], "type_ref": "builtins.tuple"}, "implicit": false, "items": [{".class": "TypeVarType", "fullname": "dynamic-scheme.T", "id": -1, "name": "T", "upper_bound": "builtins.object", "values": [], "variance": 0}, "builtins.int"]}], "type_ref": "builtins.list"}, "variables": []}, "variables": [{".class": "TypeVarDef", "fullname": "dynamic-scheme.T", "id": -1, "name": "T", "upper_bound": "builtins.object", "values": [], "variance": 0}]}}}, "pattern_parser": {".class": "SymbolTableNode", "kind": "Gdef", "node": {".class": "FuncDef", "arg_kinds": [0], "arg_names": ["pattern"], "flags": [], "fullname": "dynamic-scheme.pattern_parser", "name": "pattern_parser", "type": {".class": "CallableType", "arg_kinds": [0], "arg_names": ["pattern"], "arg_types": ["builtins.str"], "bound_args": [], "def_extras": {"first_arg": null}, "fallback": "builtins.function", "implicit": false, "is_ellipsis_args": false, "name": "pattern_parser", "ret_type": {".class": "CallableType", "arg_kinds": [0, 0], "arg_names": [null, null], "arg_types": ["builtins.str", "builtins.int"], "bound_args": [], "def_extras": {}, "fallback": "builtins.function", "implicit": false, "is_ellipsis_args": false, "name": null, "ret_type": {".class": "Instance", "args": [{".class": "TupleType", "fallback": {".class": "Instance", "args": [{".class": "AnyType", "missing_import_name": null, "source_any": null, "type_of_any": 6}], "type_ref": "builtins.tuple"}, "implicit": false, "items": ["builtins.str", "builtins.int"]}], "type_ref": "builtins.list"}, "variables": []}, "variables": []}}}, "prepend": {".class": "SymbolTableNode", "kind": "Gdef", "node": {".class": "FuncDef", "arg_kinds": [0, 0], "arg_names": ["s", "r"], "flags": [], "fullname": "dynamic-scheme.prepend", "name": "prepend", "type": {".class": "CallableType", "arg_kinds": [0, 0], "arg_names": ["s", "r"], "arg_types": ["builtins.str", {".class": "Instance", "args": [{".class": "TupleType", "fallback": {".class": "Instance", "args": [{".class": "AnyType", "missing_import_name": null, "source_any": null, "type_of_any": 6}], "type_ref": "builtins.tuple"}, "implicit": false, "items": ["builtins.str", "builtins.int"]}], "type_ref": "builtins.list"}], "bound_args": [], "def_extras": {"first_arg": null}, "fallback": "builtins.function", "implicit": false, "is_ellipsis_args": false, "name": "prepend", "ret_type": {".class": "Instance", "args": [{".class": "TupleType", "fallback": {".class": "Instance", "args": [{".class": "AnyType", "missing_import_name": null, "source_any": null, "type_of_any": 6}], "type_ref": "builtins.tuple"}, "implicit": false, "items": ["builtins.str", "builtins.int"]}], "type_ref": "builtins.list"}, "variables": []}}}, "repeat_parser": {".class": "SymbolTableNode", "kind": "Gdef", "node": {".class": "FuncDef", "arg_kinds": [0], "arg_names": ["p"], "flags": [], "fullname": "dynamic-scheme.repeat_parser", "name": "repeat_parser", "type": {".class": "CallableType", "arg_kinds": [0], "arg_names": ["p"], "arg_types": [{".class": "CallableType", "arg_kinds": [0, 0], "arg_names": [null, null], "arg_types": ["builtins.str", "builtins.int"], "bound_args": [], "def_extras": {}, "fallback": "builtins.function", "implicit": false, "is_ellipsis_args": false, "name": null, "ret_type": {".class": "Instance", "args": [{".class": "TupleType", "fallback": {".class": "Instance", "args": [{".class": "AnyType", "missing_import_name": null, "source_any": null, "type_of_any": 6}], "type_ref": "builtins.tuple"}, "implicit": false, "items": ["builtins.str", "builtins.int"]}], "type_ref": "builtins.list"}, "variables": []}], "bound_args": [], "def_extras": {"first_arg": null}, "fallback": "builtins.function", "implicit": false, "is_ellipsis_args": false, "name": "repeat_parser", "ret_type": {".class": "CallableType", "arg_kinds": [0, 0], "arg_names": [null, null], "arg_types": ["builtins.str", "builtins.int"], "bound_args": [], "def_extras": {}, "fallback": "builtins.function", "implicit": false, "is_ellipsis_args": false, "name": null, "ret_type": {".class": "Instance", "args": [{".class": "TupleType", "fallback": {".class": "Instance", "args": [{".class": "AnyType", "missing_import_name": null, "source_any": null, "type_of_any": 6}], "type_ref": "builtins.tuple"}, "implicit": false, "items": ["builtins.str", "builtins.int"]}], "type_ref": "builtins.list"}, "variables": []}, "variables": []}}}, "set_value": {".class": "SymbolTableNode", "kind": "Gdef", "node": {".class": "FuncDef", "arg_kinds": [0, 0], "arg_names": ["p", "v"], "flags": [], "fullname": "dynamic-scheme.set_value", "name": "set_value", "type": {".class": "CallableType", "arg_kinds": [0, 0], "arg_names": ["p", "v"], "arg_types": [{".class": "CallableType", "arg_kinds": [0, 0], "arg_names": [null, null], "arg_types": ["builtins.str", "builtins.int"], "bound_args": [], "def_extras": {}, "fallback": "builtins.function", "implicit": false, "is_ellipsis_args": false, "name": null, "ret_type": {".class": "Instance", "args": [{".class": "TupleType", "fallback": {".class": "Instance", "args": [{".class": "AnyType", "missing_import_name": null, "source_any": null, "type_of_any": 6}], "type_ref": "builtins.tuple"}, "implicit": false, "items": [{".class": "TypeVarType", "fullname": "dynamic-scheme.T", "id": -1, "name": "T", "upper_bound": "builtins.object", "values": [], "variance": 0}, "builtins.int"]}], "type_ref": "builtins.list"}, "variables": []}, {".class": "TypeVarType", "fullname": "dynamic-scheme.J", "id": -2, "name": "J", "upper_bound": "builtins.object", "values": [], "variance": 0}], "bound_args": [], "def_extras": {"first_arg": null}, "fallback": "builtins.function", "implicit": false, "is_ellipsis_args": false, "name": "set_value", "ret_type": {".class": "CallableType", "arg_kinds": [0, 0], "arg_names": [null, null], "arg_types": ["builtins.str", "builtins.int"], "bound_args": [], "def_extras": {}, "fallback": "builtins.function", "implicit": false, "is_ellipsis_args": false, "name": null, "ret_type": {".class": "Instance", "args": [{".class": "TupleType", "fallback": {".class": "Instance", "args": [{".class": "AnyType", "missing_import_name": null, "source_any": null, "type_of_any": 6}], "type_ref": "builtins.tuple"}, "implicit": false, "items": [{".class": "TypeVarType", "fullname": "dynamic-scheme.J", "id": -2, "name": "J", "upper_bound": "builtins.object", "values": [], "variance": 0}, "builtins.int"]}], "type_ref": "builtins.list"}, "variables": []}, "variables": [{".class": "TypeVarDef", "fullname": "dynamic-scheme.T", "id": -1, "name": "T", "upper_bound": "builtins.object", "values": [], "variance": 0}, {".class": "TypeVarDef", "fullname": "dynamic-scheme.J", "id": -2, "name": "J", "upper_bound": "builtins.object", "values": [], "variance": 0}]}}}, "string_parser": {".class": "SymbolTableNode", "kind": "Gdef", "node": {".class": "Var", "flags": [], "fullname": "dynamic-scheme.string_parser", "name": "string_parser", "type": {".class": "CallableType", "arg_kinds": [0, 0], "arg_names": [null, null], "arg_types": ["builtins.str", "builtins.int"], "bound_args": [], "def_extras": {}, "fallback": "builtins.function", "implicit": false, "is_ellipsis_args": false, "name": null, "ret_type": {".class": "Instance", "args": [{".class": "TupleType", "fallback": {".class": "Instance", "args": [{".class": "AnyType", "missing_import_name": null, "source_any": null, "type_of_any": 6}], "type_ref": "builtins.tuple"}, "implicit": false, "items": [{".class": "UnionType", "items": ["builtins.int", "builtins.float", "builtins.str", {".class": "Instance", "args": [{".class": "AnyType", "missing_import_name": null, "source_any": null, "type_of_any": 6}], "type_ref": "builtins.list"}]}, "builtins.int"]}], "type_ref": "builtins.list"}, "variables": []}}}, "valid_float_char": {".class": "SymbolTableNode", "kind": "Gdef", "node": {".class": "FuncDef", "arg_kinds": [0], "arg_names": ["c"], "flags": [], "fullname": "dynamic-scheme.valid_float_char", "name": "valid_float_char", "type": {".class": "CallableType", "arg_kinds": [0], "arg_names": ["c"], "arg_types": ["builtins.str"], "bound_args": [], "def_extras": {"first_arg": null}, "fallback": "builtins.function", "implicit": false, "is_ellipsis_args": false, "name": "valid_float_char", "ret_type": "builtins.bool", "variables": []}}}, "whatever_parser": {".class": "SymbolTableNode", "kind": "Gdef", "node": {".class": "FuncDef", "arg_kinds": [0, 0], "arg_names": ["s", "pos"], "flags": [], "fullname": "dynamic-scheme.whatever_parser", "name": "whatever_parser", "type": {".class": "CallableType", "arg_kinds": [0, 0], "arg_names": ["s", "pos"], "arg_types": ["builtins.str", "builtins.int"], "bound_args": [], "def_extras": {"first_arg": null}, "fallback": "builtins.function", "implicit": false, "is_ellipsis_args": false, "name": "whatever_parser", "ret_type": {".class": "Instance", "args": [{".class": "TupleType", "fallback": {".class": "Instance", "args": [{".class": "AnyType", "missing_import_name": null, "source_any": null, "type_of_any": 6}], "type_ref": "builtins.tuple"}, "implicit": false, "items": ["builtins.str", "builtins.int"]}], "type_ref": "builtins.list"}, "variables": []}}}}, "path": "./dynamic-scheme.py"}
